[
    {
        "text": "A",
        "x0": 64.881,
        "x1": 82.89,
        "top": 48.30899999999997,
        "doctop": 48.30899999999997,
        "bottom": 75.30900000000008,
        "upright": true,
        "direction": 1
    },
    {
        "text": "Simple",
        "x0": 90.396,
        "x1": 172.90800000000002,
        "top": 48.30899999999997,
        "doctop": 48.30899999999997,
        "bottom": 75.30900000000008,
        "upright": true,
        "direction": 1
    },
    {
        "text": "PDF",
        "x0": 180.414,
        "x1": 234.414,
        "top": 48.30899999999997,
        "doctop": 48.30899999999997,
        "bottom": 75.30900000000008,
        "upright": true,
        "direction": 1
    },
    {
        "text": "File",
        "x0": 241.92,
        "x1": 285.417,
        "top": 48.30899999999997,
        "doctop": 48.30899999999997,
        "bottom": 75.30900000000008,
        "upright": true,
        "direction": 1
    },
    {
        "text": "This",
        "x0": 72.03,
        "x1": 90.92,
        "top": 95.4620000000001,
        "doctop": 95.4620000000001,
        "bottom": 105.4620000000001,
        "upright": true,
        "direction": 1
    },
    {
        "text": "is",
        "x0": 93.7,
        "x1": 100.92,
        "top": 95.4620000000001,
        "doctop": 95.4620000000001,
        "bottom": 105.4620000000001,
        "upright": true,
        "direction": 1
    },
    {
        "text": "a",
        "x0": 103.7,
        "x1": 109.26,
        "top": 95.4620000000001,
        "doctop": 95.4620000000001,
        "bottom": 105.4620000000001,
        "upright": true,
        "direction": 1
    },
    {
        "text": "small",
        "x0": 112.04,
        "x1": 135.37,
        "top": 95.4620000000001,
        "doctop": 95.4620000000001,
        "bottom": 105.4620000000001,
        "upright": true,
        "direction": 1
    },
    {
        "text": "demonstration",
        "x0": 138.15,
        "x1": 201.51000000000002,
        "top": 95.4620000000001,
        "doctop": 95.4620000000001,
        "bottom": 105.4620000000001,
        "upright": true,
        "direction": 1
    },
    {
        "text": ".pdf",
        "x0": 204.29000000000002,
        "x1": 220.97000000000003,
        "top": 95.4620000000001,
        "doctop": 95.4620000000001,
        "bottom": 105.4620000000001,
        "upright": true,
        "direction": 1
    },
    {
        "text": "file",
        "x0": 223.75000000000003,
        "x1": 236.53000000000003,
        "top": 95.4620000000001,
        "doctop": 95.4620000000001,
        "bottom": 105.4620000000001,
        "upright": true,
        "direction": 1
    },
    {
        "text": "-",
        "x0": 239.31000000000003,
        "x1": 242.64000000000004,
        "top": 95.4620000000001,
        "doctop": 95.4620000000001,
        "bottom": 105.4620000000001,
        "upright": true,
        "direction": 1
    },
    {
        "text": "just",
        "x0": 72.03,
        "x1": 87.59,
        "top": 119.3660000000001,
        "doctop": 119.3660000000001,
        "bottom": 129.3660000000001,
        "upright": true,
        "direction": 1
    },
    {
        "text": "for",
        "x0": 90.37,
        "x1": 102.04,
        "top": 119.3660000000001,
        "doctop": 119.3660000000001,
        "bottom": 129.3660000000001,
        "upright": true,
        "direction": 1
    },
    {
        "text": "use",
        "x0": 104.82,
        "x1": 120.94,
        "top": 119.3660000000001,
        "doctop": 119.3660000000001,
        "bottom": 129.3660000000001,
        "upright": true,
        "direction": 1
    },
    {
        "text": "in",
        "x0": 123.72,
        "x1": 131.5,
        "top": 119.3660000000001,
        "doctop": 119.3660000000001,
        "bottom": 129.3660000000001,
        "upright": true,
        "direction": 1
    },
    {
        "text": "the",
        "x0": 134.28,
        "x1": 148.18,
        "top": 119.3660000000001,
        "doctop": 119.3660000000001,
        "bottom": 129.3660000000001,
        "upright": true,
        "direction": 1
    },
    {
        "text": "Virtual",
        "x0": 150.96,
        "x1": 179.3,
        "top": 119.3660000000001,
        "doctop": 119.3660000000001,
        "bottom": 129.3660000000001,
        "upright": true,
        "direction": 1
    },
    {
        "text": "Mechanics",
        "x0": 182.08,
        "x1": 229.87000000000003,
        "top": 119.3660000000001,
        "doctop": 119.3660000000001,
        "bottom": 129.3660000000001,
        "upright": true,
        "direction": 1
    },
    {
        "text": "tutorials.",
        "x0": 232.65000000000003,
        "x1": 270.44000000000005,
        "top": 119.3660000000001,
        "doctop": 119.3660000000001,
        "bottom": 129.3660000000001,
        "upright": true,
        "direction": 1
    },
    {
        "text": "More",
        "x0": 273.22,
        "x1": 296.00000000000006,
        "top": 119.3660000000001,
        "doctop": 119.3660000000001,
        "bottom": 129.3660000000001,
        "upright": true,
        "direction": 1
    },
    {
        "text": "text.",
        "x0": 298.7800000000001,
        "x1": 317.68000000000006,
        "top": 119.3660000000001,
        "doctop": 119.3660000000001,
        "bottom": 129.3660000000001,
        "upright": true,
        "direction": 1
    },
    {
        "text": "And",
        "x0": 320.4600000000001,
        "x1": 338.2500000000001,
        "top": 119.3660000000001,
        "doctop": 119.3660000000001,
        "bottom": 129.3660000000001,
        "upright": true,
        "direction": 1
    },
    {
        "text": "more",
        "x0": 341.0300000000001,
        "x1": 363.81000000000006,
        "top": 119.3660000000001,
        "doctop": 119.3660000000001,
        "bottom": 129.3660000000001,
        "upright": true,
        "direction": 1
    },
    {
        "text": "text.",
        "x0": 72.03,
        "x1": 90.93,
        "top": 131.3180000000001,
        "doctop": 131.3180000000001,
        "bottom": 141.3180000000001,
        "upright": true,
        "direction": 1
    },
    {
        "text": "And",
        "x0": 93.71000000000001,
        "x1": 111.5,
        "top": 131.3180000000001,
        "doctop": 131.3180000000001,
        "bottom": 141.3180000000001,
        "upright": true,
        "direction": 1
    },
    {
        "text": "more",
        "x0": 114.28,
        "x1": 137.06,
        "top": 131.3180000000001,
        "doctop": 131.3180000000001,
        "bottom": 141.3180000000001,
        "upright": true,
        "direction": 1
    },
    {
        "text": "text.",
        "x0": 139.84,
        "x1": 158.74,
        "top": 131.3180000000001,
        "doctop": 131.3180000000001,
        "bottom": 141.3180000000001,
        "upright": true,
        "direction": 1
    },
    {
        "text": "And",
        "x0": 161.52,
        "x1": 179.31,
        "top": 131.3180000000001,
        "doctop": 131.3180000000001,
        "bottom": 141.3180000000001,
        "upright": true,
        "direction": 1
    },
    {
        "text": "more",
        "x0": 182.09000000000003,
        "x1": 204.87000000000003,
        "top": 131.3180000000001,
        "doctop": 131.3180000000001,
        "bottom": 141.3180000000001,
        "upright": true,
        "direction": 1
    },
    {
        "text": "text.",
        "x0": 207.65000000000003,
        "x1": 226.55000000000004,
        "top": 131.3180000000001,
        "doctop": 131.3180000000001,
        "bottom": 141.3180000000001,
        "upright": true,
        "direction": 1
    },
    {
        "text": "And",
        "x0": 229.33000000000004,
        "x1": 247.12000000000003,
        "top": 131.3180000000001,
        "doctop": 131.3180000000001,
        "bottom": 141.3180000000001,
        "upright": true,
        "direction": 1
    },
    {
        "text": "more",
        "x0": 249.90000000000003,
        "x1": 272.68000000000006,
        "top": 131.3180000000001,
        "doctop": 131.3180000000001,
        "bottom": 141.3180000000001,
        "upright": true,
        "direction": 1
    },
    {
        "text": "text.",
        "x0": 275.46000000000004,
        "x1": 294.36,
        "top": 131.3180000000001,
        "doctop": 131.3180000000001,
        "bottom": 141.3180000000001,
        "upright": true,
        "direction": 1
    },
    {
        "text": "And",
        "x0": 72.03,
        "x1": 89.82000000000001,
        "top": 155.2220000000001,
        "doctop": 155.2220000000001,
        "bottom": 165.2220000000001,
        "upright": true,
        "direction": 1
    },
    {
        "text": "more",
        "x0": 92.6,
        "x1": 115.38,
        "top": 155.2220000000001,
        "doctop": 155.2220000000001,
        "bottom": 165.2220000000001,
        "upright": true,
        "direction": 1
    },
    {
        "text": "text.",
        "x0": 118.16,
        "x1": 137.06,
        "top": 155.2220000000001,
        "doctop": 155.2220000000001,
        "bottom": 165.2220000000001,
        "upright": true,
        "direction": 1
    },
    {
        "text": "And",
        "x0": 139.84,
        "x1": 157.63,
        "top": 155.2220000000001,
        "doctop": 155.2220000000001,
        "bottom": 165.2220000000001,
        "upright": true,
        "direction": 1
    },
    {
        "text": "more",
        "x0": 160.41000000000003,
        "x1": 183.19,
        "top": 155.2220000000001,
        "doctop": 155.2220000000001,
        "bottom": 165.2220000000001,
        "upright": true,
        "direction": 1
    },
    {
        "text": "text.",
        "x0": 185.97000000000003,
        "x1": 204.87,
        "top": 155.2220000000001,
        "doctop": 155.2220000000001,
        "bottom": 165.2220000000001,
        "upright": true,
        "direction": 1
    },
    {
        "text": "And",
        "x0": 207.65,
        "x1": 225.44,
        "top": 155.2220000000001,
        "doctop": 155.2220000000001,
        "bottom": 165.2220000000001,
        "upright": true,
        "direction": 1
    },
    {
        "text": "more",
        "x0": 228.22,
        "x1": 251.00000000000003,
        "top": 155.2220000000001,
        "doctop": 155.2220000000001,
        "bottom": 165.2220000000001,
        "upright": true,
        "direction": 1
    },
    {
        "text": "text.",
        "x0": 253.78000000000003,
        "x1": 272.68,
        "top": 155.2220000000001,
        "doctop": 155.2220000000001,
        "bottom": 165.2220000000001,
        "upright": true,
        "direction": 1
    },
    {
        "text": "And",
        "x0": 275.46000000000004,
        "x1": 293.25000000000006,
        "top": 155.2220000000001,
        "doctop": 155.2220000000001,
        "bottom": 165.2220000000001,
        "upright": true,
        "direction": 1
    },
    {
        "text": "more",
        "x0": 296.03000000000003,
        "x1": 318.81000000000006,
        "top": 155.2220000000001,
        "doctop": 155.2220000000001,
        "bottom": 165.2220000000001,
        "upright": true,
        "direction": 1
    },
    {
        "text": "text.",
        "x0": 321.59000000000003,
        "x1": 340.49,
        "top": 155.2220000000001,
        "doctop": 155.2220000000001,
        "bottom": 165.2220000000001,
        "upright": true,
        "direction": 1
    },
    {
        "text": "And",
        "x0": 343.27,
        "x1": 361.06,
        "top": 155.2220000000001,
        "doctop": 155.2220000000001,
        "bottom": 165.2220000000001,
        "upright": true,
        "direction": 1
    },
    {
        "text": "more",
        "x0": 363.84,
        "x1": 386.61999999999995,
        "top": 155.2220000000001,
        "doctop": 155.2220000000001,
        "bottom": 165.2220000000001,
        "upright": true,
        "direction": 1
    },
    {
        "text": "text.",
        "x0": 72.03,
        "x1": 90.93,
        "top": 167.1740000000001,
        "doctop": 167.1740000000001,
        "bottom": 177.1740000000001,
        "upright": true,
        "direction": 1
    },
    {
        "text": "And",
        "x0": 93.71000000000001,
        "x1": 111.5,
        "top": 167.1740000000001,
        "doctop": 167.1740000000001,
        "bottom": 177.1740000000001,
        "upright": true,
        "direction": 1
    },
    {
        "text": "more",
        "x0": 114.28,
        "x1": 137.06,
        "top": 167.1740000000001,
        "doctop": 167.1740000000001,
        "bottom": 177.1740000000001,
        "upright": true,
        "direction": 1
    },
    {
        "text": "text.",
        "x0": 139.84,
        "x1": 158.74,
        "top": 167.1740000000001,
        "doctop": 167.1740000000001,
        "bottom": 177.1740000000001,
        "upright": true,
        "direction": 1
    },
    {
        "text": "Boring,",
        "x0": 161.52,
        "x1": 193.20000000000002,
        "top": 167.1740000000001,
        "doctop": 167.1740000000001,
        "bottom": 177.1740000000001,
        "upright": true,
        "direction": 1
    },
    {
        "text": "zzzzz.",
        "x0": 195.98000000000002,
        "x1": 223.76000000000002,
        "top": 167.1740000000001,
        "doctop": 167.1740000000001,
        "bottom": 177.1740000000001,
        "upright": true,
        "direction": 1
    },
    {
        "text": "And",
        "x0": 226.54000000000002,
        "x1": 244.33,
        "top": 167.1740000000001,
        "doctop": 167.1740000000001,
        "bottom": 177.1740000000001,
        "upright": true,
        "direction": 1
    },
    {
        "text": "more",
        "x0": 247.11,
        "x1": 269.89000000000004,
        "top": 167.1740000000001,
        "doctop": 167.1740000000001,
        "bottom": 177.1740000000001,
        "upright": true,
        "direction": 1
    },
    {
        "text": "text.",
        "x0": 272.6700000000001,
        "x1": 291.57000000000005,
        "top": 167.1740000000001,
        "doctop": 167.1740000000001,
        "bottom": 177.1740000000001,
        "upright": true,
        "direction": 1
    },
    {
        "text": "And",
        "x0": 294.35,
        "x1": 312.14000000000004,
        "top": 167.1740000000001,
        "doctop": 167.1740000000001,
        "bottom": 177.1740000000001,
        "upright": true,
        "direction": 1
    },
    {
        "text": "more",
        "x0": 314.9200000000001,
        "x1": 337.70000000000005,
        "top": 167.1740000000001,
        "doctop": 167.1740000000001,
        "bottom": 177.1740000000001,
        "upright": true,
        "direction": 1
    },
    {
        "text": "text.",
        "x0": 340.48,
        "x1": 359.37999999999994,
        "top": 167.1740000000001,
        "doctop": 167.1740000000001,
        "bottom": 177.1740000000001,
        "upright": true,
        "direction": 1
    },
    {
        "text": "And",
        "x0": 362.1599999999999,
        "x1": 379.94999999999993,
        "top": 167.1740000000001,
        "doctop": 167.1740000000001,
        "bottom": 177.1740000000001,
        "upright": true,
        "direction": 1
    },
    {
        "text": "more",
        "x0": 72.03,
        "x1": 94.81,
        "top": 179.1260000000001,
        "doctop": 179.1260000000001,
        "bottom": 189.1260000000001,
        "upright": true,
        "direction": 1
    },
    {
        "text": "text.",
        "x0": 97.59,
        "x1": 116.49000000000001,
        "top": 179.1260000000001,
        "doctop": 179.1260000000001,
        "bottom": 189.1260000000001,
        "upright": true,
        "direction": 1
    },
    {
        "text": "And",
        "x0": 119.27000000000001,
        "x1": 137.06,
        "top": 179.1260000000001,
        "doctop": 179.1260000000001,
        "bottom": 189.1260000000001,
        "upright": true,
        "direction": 1
    },
    {
        "text": "more",
        "x0": 139.84000000000003,
        "x1": 162.62,
        "top": 179.1260000000001,
        "doctop": 179.1260000000001,
        "bottom": 189.1260000000001,
        "upright": true,
        "direction": 1
    },
    {
        "text": "text.",
        "x0": 165.40000000000003,
        "x1": 184.30000000000004,
        "top": 179.1260000000001,
        "doctop": 179.1260000000001,
        "bottom": 189.1260000000001,
        "upright": true,
        "direction": 1
    },
    {
        "text": "And",
        "x0": 187.08000000000004,
        "x1": 204.87000000000003,
        "top": 179.1260000000001,
        "doctop": 179.1260000000001,
        "bottom": 189.1260000000001,
        "upright": true,
        "direction": 1
    },
    {
        "text": "more",
        "x0": 207.65000000000003,
        "x1": 230.43000000000006,
        "top": 179.1260000000001,
        "doctop": 179.1260000000001,
        "bottom": 189.1260000000001,
        "upright": true,
        "direction": 1
    },
    {
        "text": "text.",
        "x0": 233.21000000000006,
        "x1": 252.11000000000007,
        "top": 179.1260000000001,
        "doctop": 179.1260000000001,
        "bottom": 189.1260000000001,
        "upright": true,
        "direction": 1
    },
    {
        "text": "And",
        "x0": 254.89000000000007,
        "x1": 272.68000000000006,
        "top": 179.1260000000001,
        "doctop": 179.1260000000001,
        "bottom": 189.1260000000001,
        "upright": true,
        "direction": 1
    },
    {
        "text": "more",
        "x0": 275.46000000000004,
        "x1": 298.24000000000007,
        "top": 179.1260000000001,
        "doctop": 179.1260000000001,
        "bottom": 189.1260000000001,
        "upright": true,
        "direction": 1
    },
    {
        "text": "text.",
        "x0": 301.0200000000001,
        "x1": 319.9200000000001,
        "top": 179.1260000000001,
        "doctop": 179.1260000000001,
        "bottom": 189.1260000000001,
        "upright": true,
        "direction": 1
    },
    {
        "text": "And",
        "x0": 322.7000000000001,
        "x1": 340.4900000000001,
        "top": 179.1260000000001,
        "doctop": 179.1260000000001,
        "bottom": 189.1260000000001,
        "upright": true,
        "direction": 1
    },
    {
        "text": "more",
        "x0": 343.2700000000001,
        "x1": 366.05000000000007,
        "top": 179.1260000000001,
        "doctop": 179.1260000000001,
        "bottom": 189.1260000000001,
        "upright": true,
        "direction": 1
    },
    {
        "text": "text.",
        "x0": 368.83000000000004,
        "x1": 387.72999999999996,
        "top": 179.1260000000001,
        "doctop": 179.1260000000001,
        "bottom": 189.1260000000001,
        "upright": true,
        "direction": 1
    },
    {
        "text": "And",
        "x0": 72.03,
        "x1": 89.82000000000001,
        "top": 191.0780000000001,
        "doctop": 191.0780000000001,
        "bottom": 201.0780000000001,
        "upright": true,
        "direction": 1
    },
    {
        "text": "more",
        "x0": 92.6,
        "x1": 115.38,
        "top": 191.0780000000001,
        "doctop": 191.0780000000001,
        "bottom": 201.0780000000001,
        "upright": true,
        "direction": 1
    },
    {
        "text": "text.",
        "x0": 118.16,
        "x1": 137.06,
        "top": 191.0780000000001,
        "doctop": 191.0780000000001,
        "bottom": 201.0780000000001,
        "upright": true,
        "direction": 1
    },
    {
        "text": "And",
        "x0": 139.84,
        "x1": 157.63,
        "top": 191.0780000000001,
        "doctop": 191.0780000000001,
        "bottom": 201.0780000000001,
        "upright": true,
        "direction": 1
    },
    {
        "text": "more",
        "x0": 160.41000000000003,
        "x1": 183.19,
        "top": 191.0780000000001,
        "doctop": 191.0780000000001,
        "bottom": 201.0780000000001,
        "upright": true,
        "direction": 1
    },
    {
        "text": "text.",
        "x0": 185.97000000000003,
        "x1": 204.87,
        "top": 191.0780000000001,
        "doctop": 191.0780000000001,
        "bottom": 201.0780000000001,
        "upright": true,
        "direction": 1
    },
    {
        "text": "And",
        "x0": 72.03,
        "x1": 89.82000000000001,
        "top": 214.98200000000008,
        "doctop": 214.98200000000008,
        "bottom": 224.98200000000008,
        "upright": true,
        "direction": 1
    },
    {
        "text": "more",
        "x0": 92.6,
        "x1": 115.38,
        "top": 214.98200000000008,
        "doctop": 214.98200000000008,
        "bottom": 224.98200000000008,
        "upright": true,
        "direction": 1
    },
    {
        "text": "text.",
        "x0": 118.16,
        "x1": 137.06,
        "top": 214.98200000000008,
        "doctop": 214.98200000000008,
        "bottom": 224.98200000000008,
        "upright": true,
        "direction": 1
    },
    {
        "text": "And",
        "x0": 139.84,
        "x1": 157.63,
        "top": 214.98200000000008,
        "doctop": 214.98200000000008,
        "bottom": 224.98200000000008,
        "upright": true,
        "direction": 1
    },
    {
        "text": "more",
        "x0": 160.41000000000003,
        "x1": 183.19,
        "top": 214.98200000000008,
        "doctop": 214.98200000000008,
        "bottom": 224.98200000000008,
        "upright": true,
        "direction": 1
    },
    {
        "text": "text.",
        "x0": 185.97000000000003,
        "x1": 204.87,
        "top": 214.98200000000008,
        "doctop": 214.98200000000008,
        "bottom": 224.98200000000008,
        "upright": true,
        "direction": 1
    },
    {
        "text": "And",
        "x0": 207.65,
        "x1": 225.44,
        "top": 214.98200000000008,
        "doctop": 214.98200000000008,
        "bottom": 224.98200000000008,
        "upright": true,
        "direction": 1
    },
    {
        "text": "more",
        "x0": 228.22,
        "x1": 251.00000000000003,
        "top": 214.98200000000008,
        "doctop": 214.98200000000008,
        "bottom": 224.98200000000008,
        "upright": true,
        "direction": 1
    },
    {
        "text": "text.",
        "x0": 253.78000000000003,
        "x1": 272.68,
        "top": 214.98200000000008,
        "doctop": 214.98200000000008,
        "bottom": 224.98200000000008,
        "upright": true,
        "direction": 1
    },
    {
        "text": "And",
        "x0": 275.46000000000004,
        "x1": 293.25000000000006,
        "top": 214.98200000000008,
        "doctop": 214.98200000000008,
        "bottom": 224.98200000000008,
        "upright": true,
        "direction": 1
    },
    {
        "text": "more",
        "x0": 296.03000000000003,
        "x1": 318.81000000000006,
        "top": 214.98200000000008,
        "doctop": 214.98200000000008,
        "bottom": 224.98200000000008,
        "upright": true,
        "direction": 1
    },
    {
        "text": "text.",
        "x0": 321.59000000000003,
        "x1": 340.49,
        "top": 214.98200000000008,
        "doctop": 214.98200000000008,
        "bottom": 224.98200000000008,
        "upright": true,
        "direction": 1
    },
    {
        "text": "And",
        "x0": 343.27,
        "x1": 361.06,
        "top": 214.98200000000008,
        "doctop": 214.98200000000008,
        "bottom": 224.98200000000008,
        "upright": true,
        "direction": 1
    },
    {
        "text": "more",
        "x0": 363.84,
        "x1": 386.61999999999995,
        "top": 214.98200000000008,
        "doctop": 214.98200000000008,
        "bottom": 224.98200000000008,
        "upright": true,
        "direction": 1
    },
    {
        "text": "text.",
        "x0": 72.03,
        "x1": 90.93,
        "top": 226.93400000000008,
        "doctop": 226.93400000000008,
        "bottom": 236.93400000000008,
        "upright": true,
        "direction": 1
    },
    {
        "text": "And",
        "x0": 93.71000000000001,
        "x1": 111.5,
        "top": 226.93400000000008,
        "doctop": 226.93400000000008,
        "bottom": 236.93400000000008,
        "upright": true,
        "direction": 1
    },
    {
        "text": "more",
        "x0": 114.28,
        "x1": 137.06,
        "top": 226.93400000000008,
        "doctop": 226.93400000000008,
        "bottom": 236.93400000000008,
        "upright": true,
        "direction": 1
    },
    {
        "text": "text.",
        "x0": 139.84,
        "x1": 158.74,
        "top": 226.93400000000008,
        "doctop": 226.93400000000008,
        "bottom": 236.93400000000008,
        "upright": true,
        "direction": 1
    },
    {
        "text": "And",
        "x0": 161.52,
        "x1": 179.31,
        "top": 226.93400000000008,
        "doctop": 226.93400000000008,
        "bottom": 236.93400000000008,
        "upright": true,
        "direction": 1
    },
    {
        "text": "more",
        "x0": 182.09000000000003,
        "x1": 204.87000000000003,
        "top": 226.93400000000008,
        "doctop": 226.93400000000008,
        "bottom": 236.93400000000008,
        "upright": true,
        "direction": 1
    },
    {
        "text": "text.",
        "x0": 207.65000000000003,
        "x1": 226.55000000000004,
        "top": 226.93400000000008,
        "doctop": 226.93400000000008,
        "bottom": 236.93400000000008,
        "upright": true,
        "direction": 1
    },
    {
        "text": "Even",
        "x0": 229.33000000000004,
        "x1": 252.12000000000003,
        "top": 226.93400000000008,
        "doctop": 226.93400000000008,
        "bottom": 236.93400000000008,
        "upright": true,
        "direction": 1
    },
    {
        "text": "more.",
        "x0": 254.90000000000003,
        "x1": 280.46000000000004,
        "top": 226.93400000000008,
        "doctop": 226.93400000000008,
        "bottom": 236.93400000000008,
        "upright": true,
        "direction": 1
    },
    {
        "text": "Continued",
        "x0": 283.24000000000007,
        "x1": 328.8200000000001,
        "top": 226.93400000000008,
        "doctop": 226.93400000000008,
        "bottom": 236.93400000000008,
        "upright": true,
        "direction": 1
    },
    {
        "text": "on",
        "x0": 331.6,
        "x1": 342.72,
        "top": 226.93400000000008,
        "doctop": 226.93400000000008,
        "bottom": 236.93400000000008,
        "upright": true,
        "direction": 1
    },
    {
        "text": "page",
        "x0": 345.5,
        "x1": 367.74,
        "top": 226.93400000000008,
        "doctop": 226.93400000000008,
        "bottom": 236.93400000000008,
        "upright": true,
        "direction": 1
    },
    {
        "text": "2",
        "x0": 370.52,
        "x1": 376.08,
        "top": 226.93400000000008,
        "doctop": 226.93400000000008,
        "bottom": 236.93400000000008,
        "upright": true,
        "direction": 1
    },
    {
        "text": "...",
        "x0": 378.85999999999996,
        "x1": 387.1999999999999,
        "top": 226.93400000000008,
        "doctop": 226.93400000000008,
        "bottom": 236.93400000000008,
        "upright": true,
        "direction": 1
    }
]